{
	"animations": [
		{
			"offsets": [
				0,
				0
			],
			"loop": false,
			"fps": 24,
			"anim": "danceLeft",
			"indices": [
				0,
				1,
				2,
				3,
				4,
				5,
				6,
				7,
				8,
				9
			],
			"name": "pico idle"
		},
		{
			"offsets": [
				0,
				0
			],
			"loop": false,
			"fps": 24,
			"anim": "danceRight",
			"indices": [
				10,
				11,
				12,
				13,
				14,
				15,
				16,
				17,
				18,
				19
			],
			"name": "pico idle"
		},
		{
			"loop": false,
			"offsets": [
				0,
				0
			],
			"anim": "danceLeft-alt",
			"fps": 24,
			"name": "pico alt idle",
			"indices": [
				0,
				1,
				2,
				3,
				4,
				5,
				6,
				7,
				8,
				9
			]
		},
		{
			"loop": false,
			"offsets": [
				0,
				0
			],
			"anim": "danceRight-alt",
			"fps": 24,
			"name": "pico alt idle",
			"indices": [
				10,
				11,
				12,
				13,
				14,
				15,
				16,
				17,
				18,
				19
			]
		},
		{
			"loop": false,
			"offsets": [
				0,
				30
			],
			"anim": "offended",
			"fps": 24,
			"name": "pico offended",
			"indices": []
		}
	],
	"no_antialiasing": false,
	"image": "characters/pico",
	"position": [
		0,
		-60
	],
	"healthicon": "picosoft",
	"flip_x": false,
	"healthbar_colors": [
		60,
		90,
		62
	],
	"camera_position": [
		0,
		0
	],
	"sing_duration": 6.1,
	"scale": 1
}