<?xml version="1.0" encoding="utf-8"?>
<TextureAtlas imagePath="zuki-pibby.png">
	<!-- Created with Adobe Animate version 19.1.0.349 -->
	<!-- http://www.adobe.com/products/animate.html -->
	<SubTexture name="Idle0000" x="20" y="20" width="332" height="569" frameX="-14" frameY="-19" frameWidth="346" frameHeight="595"/>
	<SubTexture name="Idle0001" x="20" y="20" width="332" height="569" frameX="-14" frameY="-19" frameWidth="346" frameHeight="595"/>
	<SubTexture name="Idle0002" x="372" y="20" width="331" height="584" frameX="-9" frameY="-4" frameWidth="346" frameHeight="595"/>
	<SubTexture name="Idle0003" x="372" y="20" width="331" height="584" frameX="-9" frameY="-4" frameWidth="346" frameHeight="595"/>
	<SubTexture name="Idle0004" x="723" y="20" width="336" height="587" frameX="0" frameY="-1" frameWidth="346" frameHeight="595"/>
	<SubTexture name="Idle0005" x="723" y="20" width="336" height="587" frameX="0" frameY="-1" frameWidth="346" frameHeight="595"/>
	<SubTexture name="Idle0006" x="1079" y="20" width="332" height="595" frameX="-7" frameY="0" frameWidth="346" frameHeight="595"/>
	<SubTexture name="Idle0007" x="1079" y="20" width="332" height="595" frameX="-7" frameY="0" frameWidth="346" frameHeight="595"/>
	<SubTexture name="Idle0008" x="1431" y="20" width="333" height="588" frameX="-7" frameY="0" frameWidth="346" frameHeight="595"/>
	<SubTexture name="Idle0009" x="1431" y="20" width="333" height="588" frameX="-7" frameY="0" frameWidth="346" frameHeight="595"/>
	<SubTexture name="Idle0010" x="1784" y="20" width="343" height="588" frameX="-3" frameY="0" frameWidth="346" frameHeight="595"/>
	<SubTexture name="Idle0011" x="1784" y="20" width="343" height="588" frameX="-3" frameY="0" frameWidth="346" frameHeight="595"/>
	<SubTexture name="Idle0012" x="2147" y="20" width="337" height="588" frameX="0" frameY="0" frameWidth="346" frameHeight="595"/>
	<SubTexture name="Idle0013" x="2147" y="20" width="337" height="588" frameX="0" frameY="0" frameWidth="346" frameHeight="595"/>
	<SubTexture name="singDOWN0000" x="2504" y="20" width="340" height="506" frameX="-19" frameY="-17" frameWidth="359" frameHeight="530"/>
	<SubTexture name="singDOWN0001" x="2504" y="20" width="340" height="506" frameX="-19" frameY="-17" frameWidth="359" frameHeight="530"/>
	<SubTexture name="singDOWN0002" x="2864" y="20" width="336" height="523" frameX="-3" frameY="0" frameWidth="359" frameHeight="530"/>
	<SubTexture name="singDOWN0003" x="2864" y="20" width="336" height="523" frameX="-3" frameY="0" frameWidth="359" frameHeight="530"/>
	<SubTexture name="singDOWN0004" x="3220" y="20" width="344" height="523" frameX="0" frameY="0" frameWidth="359" frameHeight="530"/>
	<SubTexture name="singDOWN0005" x="3220" y="20" width="344" height="523" frameX="0" frameY="0" frameWidth="359" frameHeight="530"/>
	<SubTexture name="singDOWN0006" x="3584" y="20" width="334" height="530" frameX="-11" frameY="0" frameWidth="359" frameHeight="530"/>
	<SubTexture name="singDOWN0007" x="3584" y="20" width="334" height="530" frameX="-11" frameY="0" frameWidth="359" frameHeight="530"/>
	<SubTexture name="singDOWN0008" x="20" y="635" width="336" height="523" frameX="-3" frameY="0" frameWidth="359" frameHeight="530"/>
	<SubTexture name="singDOWN0009" x="20" y="635" width="336" height="523" frameX="-3" frameY="0" frameWidth="359" frameHeight="530"/>
	<SubTexture name="singDOWN0010" x="376" y="635" width="344" height="523" frameX="0" frameY="0" frameWidth="359" frameHeight="530"/>
	<SubTexture name="singDOWN0011" x="376" y="635" width="344" height="523" frameX="0" frameY="0" frameWidth="359" frameHeight="530"/>
	<SubTexture name="singDOWN0012" x="740" y="635" width="334" height="523" frameX="-11" frameY="0" frameWidth="359" frameHeight="530"/>
	<SubTexture name="singDOWN0013" x="740" y="635" width="334" height="523" frameX="-11" frameY="0" frameWidth="359" frameHeight="530"/>
	<SubTexture name="singDOWN0014" x="1094" y="635" width="336" height="530" frameX="-3" frameY="0" frameWidth="359" frameHeight="530"/>
	<SubTexture name="singLEFT0000" x="1450" y="635" width="321" height="583" frameX="0" frameY="-4" frameWidth="341" frameHeight="587"/>
	<SubTexture name="singLEFT0001" x="1450" y="635" width="321" height="583" frameX="0" frameY="-4" frameWidth="341" frameHeight="587"/>
	<SubTexture name="singLEFT0002" x="1791" y="635" width="323" height="587" frameX="-18" frameY="0" frameWidth="341" frameHeight="587"/>
	<SubTexture name="singLEFT0003" x="1791" y="635" width="323" height="587" frameX="-18" frameY="0" frameWidth="341" frameHeight="587"/>
	<SubTexture name="singLEFT0004" x="2134" y="635" width="328" height="587" frameX="-13" frameY="0" frameWidth="341" frameHeight="587"/>
	<SubTexture name="singLEFT0005" x="2134" y="635" width="328" height="587" frameX="-13" frameY="0" frameWidth="341" frameHeight="587"/>
	<SubTexture name="singLEFT0006" x="2482" y="635" width="327" height="587" frameX="-14" frameY="0" frameWidth="341" frameHeight="587"/>
	<SubTexture name="singLEFT0007" x="2482" y="635" width="327" height="587" frameX="-14" frameY="0" frameWidth="341" frameHeight="587"/>
	<SubTexture name="singLEFT0008" x="2829" y="635" width="323" height="587" frameX="-18" frameY="0" frameWidth="341" frameHeight="587"/>
	<SubTexture name="singLEFT0009" x="2829" y="635" width="323" height="587" frameX="-18" frameY="0" frameWidth="341" frameHeight="587"/>
	<SubTexture name="singLEFT0010" x="3172" y="635" width="328" height="587" frameX="-13" frameY="0" frameWidth="341" frameHeight="587"/>
	<SubTexture name="singLEFT0011" x="3172" y="635" width="328" height="587" frameX="-13" frameY="0" frameWidth="341" frameHeight="587"/>
	<SubTexture name="singLEFT0012" x="3520" y="635" width="327" height="587" frameX="-14" frameY="0" frameWidth="341" frameHeight="587"/>
	<SubTexture name="singLEFT0013" x="3520" y="635" width="327" height="587" frameX="-14" frameY="0" frameWidth="341" frameHeight="587"/>
	<SubTexture name="singLEFT0014" x="1791" y="635" width="323" height="587" frameX="-18" frameY="0" frameWidth="341" frameHeight="587"/>
	<SubTexture name="singRIGHT0000" x="20" y="1242" width="329" height="586" frameX="-10" frameY="0" frameWidth="341" frameHeight="586"/>
	<SubTexture name="singRIGHT0001" x="20" y="1242" width="329" height="586" frameX="-10" frameY="0" frameWidth="341" frameHeight="586"/>
	<SubTexture name="singRIGHT0002" x="369" y="1242" width="335" height="586" frameX="-6" frameY="0" frameWidth="341" frameHeight="586"/>
	<SubTexture name="singRIGHT0003" x="724" y="1242" width="335" height="582" frameX="-4" frameY="-4" frameWidth="341" frameHeight="586"/>
	<SubTexture name="singRIGHT0004" x="1079" y="1242" width="330" height="582" frameX="-4" frameY="-4" frameWidth="341" frameHeight="586"/>
	<SubTexture name="singRIGHT0005" x="1429" y="1242" width="337" height="582" frameX="0" frameY="-4" frameWidth="341" frameHeight="586"/>
	<SubTexture name="singRIGHT0006" x="1786" y="1242" width="339" height="582" frameX="0" frameY="-4" frameWidth="341" frameHeight="586"/>
	<SubTexture name="singRIGHT0007" x="2145" y="1242" width="329" height="582" frameX="-10" frameY="-4" frameWidth="341" frameHeight="586"/>
	<SubTexture name="singRIGHT0008" x="2494" y="1242" width="329" height="582" frameX="-10" frameY="-4" frameWidth="341" frameHeight="586"/>
	<SubTexture name="singRIGHT0009" x="724" y="1242" width="335" height="582" frameX="-4" frameY="-4" frameWidth="341" frameHeight="586"/>
	<SubTexture name="singRIGHT0010" x="1079" y="1242" width="330" height="582" frameX="-4" frameY="-4" frameWidth="341" frameHeight="586"/>
	<SubTexture name="singRIGHT0011" x="1429" y="1242" width="337" height="582" frameX="0" frameY="-4" frameWidth="341" frameHeight="586"/>
	<SubTexture name="singRIGHT0012" x="1786" y="1242" width="339" height="582" frameX="0" frameY="-4" frameWidth="341" frameHeight="586"/>
	<SubTexture name="singRIGHT0013" x="2145" y="1242" width="329" height="582" frameX="-10" frameY="-4" frameWidth="341" frameHeight="586"/>
	<SubTexture name="singRIGHT0014" x="2494" y="1242" width="329" height="582" frameX="-10" frameY="-4" frameWidth="341" frameHeight="586"/>
	<SubTexture name="singUP0000" x="2843" y="1242" width="277" height="576" frameX="-26" frameY="-11" frameWidth="307" frameHeight="593"/>
	<SubTexture name="singUP0001" x="2843" y="1242" width="277" height="576" frameX="-26" frameY="-11" frameWidth="307" frameHeight="593"/>
	<SubTexture name="singUP0002" x="3140" y="1242" width="307" height="586" frameX="0" frameY="0" frameWidth="307" frameHeight="593"/>
	<SubTexture name="singUP0003" x="3140" y="1242" width="307" height="586" frameX="0" frameY="0" frameWidth="307" frameHeight="593"/>
	<SubTexture name="singUP0004" x="3467" y="1242" width="302" height="586" frameX="-5" frameY="0" frameWidth="307" frameHeight="593"/>
	<SubTexture name="singUP0005" x="3467" y="1242" width="302" height="586" frameX="-5" frameY="0" frameWidth="307" frameHeight="593"/>
	<SubTexture name="singUP0006" x="20" y="1848" width="306" height="593" frameX="-1" frameY="0" frameWidth="307" frameHeight="593"/>
	<SubTexture name="singUP0007" x="20" y="1848" width="306" height="593" frameX="-1" frameY="0" frameWidth="307" frameHeight="593"/>
	<SubTexture name="singUP0008" x="346" y="1848" width="307" height="586" frameX="0" frameY="0" frameWidth="307" frameHeight="593"/>
	<SubTexture name="singUP0009" x="346" y="1848" width="307" height="586" frameX="0" frameY="0" frameWidth="307" frameHeight="593"/>
	<SubTexture name="singUP0010" x="673" y="1848" width="302" height="586" frameX="-5" frameY="0" frameWidth="307" frameHeight="593"/>
	<SubTexture name="singUP0011" x="673" y="1848" width="302" height="586" frameX="-5" frameY="0" frameWidth="307" frameHeight="593"/>
	<SubTexture name="singUP0012" x="995" y="1848" width="306" height="586" frameX="-1" frameY="0" frameWidth="307" frameHeight="593"/>
	<SubTexture name="singUP0013" x="995" y="1848" width="306" height="586" frameX="-1" frameY="0" frameWidth="307" frameHeight="593"/>
	<SubTexture name="singUP0014" x="1321" y="1848" width="307" height="593"/>
</TextureAtlas>
